setup.cfg
setup.py
macman/__init__.py
macman/dialog.py
macman/files.py
macman/logs.py
macman/misc.py
macman/munki.py
macman/network.py
macman/plists.py
macman/remoteaccess.py
macman/sysinfo.py
macman/systime.py
macman/users.py
macman.egg-info/PKG-INFO
macman.egg-info/SOURCES.txt
macman.egg-info/dependency_links.txt
macman.egg-info/not-zip-safe
macman.egg-info/top_level.txt