Metadata-Version: 1.0
Name: macman
Version: 5.6
Summary: OSX Management tools
Home-page: UNKNOWN
Author: UNKNOWN
Author-email: UNKNOWN
License: MIT
Platform: UNKNOWN
